{"nodes":[{"id":"migrations_0068_investments","label":"0068_investments.sql","file_type":"code","source_file":"P:\\Projects\\Mycelium\\supabase\\migrations\\0068_investments.sql","source_location":"L1"},{"id":"migrations_0068_investments_investments","label":"investments","file_type":"code","source_file":"P:\\Projects\\Mycelium\\supabase\\migrations\\0068_investments.sql","source_location":"L1"}],"edges":[{"source":"migrations_0068_investments","target":"migrations_0068_investments_investments","relation":"contains","confidence":"EXTRACTED","source_file":"P:\\Projects\\Mycelium\\supabase\\migrations\\0068_investments.sql","source_location":"L1","weight":1}]}