{"nodes":[{"id":"memory_types","label":"types.ts","file_type":"code","source_file":"P:\\Projects\\Mycelium\\lib\\memory\\types.ts","source_location":"L1"},{"id":"memory_types_chunkmeta","label":"ChunkMeta","file_type":"code","source_file":"P:\\Projects\\Mycelium\\lib\\memory\\types.ts","source_location":"L1"},{"id":"memory_types_capturesource","label":"CaptureSource","file_type":"code","source_file":"P:\\Projects\\Mycelium\\lib\\memory\\types.ts","source_location":"L10"},{"id":"memory_types_tasksource","label":"TaskSource","file_type":"code","source_file":"P:\\Projects\\Mycelium\\lib\\memory\\types.ts","source_location":"L19"},{"id":"memory_types_othersource","label":"OtherSource","file_type":"code","source_file":"P:\\Projects\\Mycelium\\lib\\memory\\types.ts","source_location":"L30"},{"id":"memory_types_enrichedsource","label":"EnrichedSource","file_type":"code","source_file":"P:\\Projects\\Mycelium\\lib\\memory\\types.ts","source_location":"L36"},{"id":"memory_types_searchmatch","label":"SearchMatch","file_type":"code","source_file":"P:\\Projects\\Mycelium\\lib\\memory\\types.ts","source_location":"L38"},{"id":"memory_types_asksource","label":"AskSource","file_type":"code","source_file":"P:\\Projects\\Mycelium\\lib\\memory\\types.ts","source_location":"L43"}],"edges":[{"source":"memory_types","target":"memory_types_chunkmeta","relation":"contains","confidence":"EXTRACTED","source_file":"P:\\Projects\\Mycelium\\lib\\memory\\types.ts","source_location":"L1","weight":1},{"source":"memory_types","target":"memory_types_capturesource","relation":"contains","confidence":"EXTRACTED","source_file":"P:\\Projects\\Mycelium\\lib\\memory\\types.ts","source_location":"L10","weight":1},{"source":"memory_types","target":"memory_types_tasksource","relation":"contains","confidence":"EXTRACTED","source_file":"P:\\Projects\\Mycelium\\lib\\memory\\types.ts","source_location":"L19","weight":1},{"source":"memory_types","target":"memory_types_othersource","relation":"contains","confidence":"EXTRACTED","source_file":"P:\\Projects\\Mycelium\\lib\\memory\\types.ts","source_location":"L30","weight":1},{"source":"memory_types","target":"memory_types_enrichedsource","relation":"contains","confidence":"EXTRACTED","source_file":"P:\\Projects\\Mycelium\\lib\\memory\\types.ts","source_location":"L36","weight":1},{"source":"memory_types","target":"memory_types_searchmatch","relation":"contains","confidence":"EXTRACTED","source_file":"P:\\Projects\\Mycelium\\lib\\memory\\types.ts","source_location":"L38","weight":1},{"source":"memory_types","target":"memory_types_asksource","relation":"contains","confidence":"EXTRACTED","source_file":"P:\\Projects\\Mycelium\\lib\\memory\\types.ts","source_location":"L43","weight":1}]}