{"nodes":[{"id":"dashboard_toprail","label":"TopRail.tsx","file_type":"code","source_file":"P:\\Projects\\Mycelium\\components\\dashboard\\TopRail.tsx","source_location":"L1"},{"id":"dashboard_toprail_navtab","label":"NavTab","file_type":"code","source_file":"P:\\Projects\\Mycelium\\components\\dashboard\\TopRail.tsx","source_location":"L9"},{"id":"dashboard_toprail_tabs","label":"TABS","file_type":"code","source_file":"P:\\Projects\\Mycelium\\components\\dashboard\\TopRail.tsx","source_location":"L16"},{"id":"dashboard_toprail_toprail","label":"TopRail()","file_type":"code","source_file":"P:\\Projects\\Mycelium\\components\\dashboard\\TopRail.tsx","source_location":"L36"}],"edges":[{"source":"dashboard_toprail","target":"react","relation":"imports_from","confidence":"EXTRACTED","source_file":"P:\\Projects\\Mycelium\\components\\dashboard\\TopRail.tsx","source_location":"L3","weight":1},{"source":"dashboard_toprail","target":"link","relation":"imports_from","confidence":"EXTRACTED","source_file":"P:\\Projects\\Mycelium\\components\\dashboard\\TopRail.tsx","source_location":"L4","weight":1},{"source":"dashboard_toprail","target":"navigation","relation":"imports_from","confidence":"EXTRACTED","source_file":"P:\\Projects\\Mycelium\\components\\dashboard\\TopRail.tsx","source_location":"L5","weight":1},{"source":"dashboard_toprail","target":"p_projects_mycelium_components_dashboard_wordmark_tsx","relation":"imports_from","confidence":"EXTRACTED","source_file":"P:\\Projects\\Mycelium\\components\\dashboard\\TopRail.tsx","source_location":"L6","weight":1},{"source":"dashboard_toprail","target":"dashboard_wordmark_wordmark","relation":"imports","confidence":"EXTRACTED","source_file":"P:\\Projects\\Mycelium\\components\\dashboard\\TopRail.tsx","source_location":"L6","weight":1},{"source":"dashboard_toprail","target":"p_projects_mycelium_lib_nav_sections_ts","relation":"imports_from","confidence":"EXTRACTED","source_file":"P:\\Projects\\Mycelium\\components\\dashboard\\TopRail.tsx","source_location":"L7","weight":1},{"source":"dashboard_toprail","target":"nav_sections_sections","relation":"imports","confidence":"EXTRACTED","source_file":"P:\\Projects\\Mycelium\\components\\dashboard\\TopRail.tsx","source_location":"L7","weight":1},{"source":"dashboard_toprail","target":"dashboard_toprail_navtab","relation":"contains","confidence":"EXTRACTED","source_file":"P:\\Projects\\Mycelium\\components\\dashboard\\TopRail.tsx","source_location":"L9","weight":1},{"source":"dashboard_toprail","target":"dashboard_toprail_tabs","relation":"contains","confidence":"EXTRACTED","source_file":"P:\\Projects\\Mycelium\\components\\dashboard\\TopRail.tsx","source_location":"L16","weight":1},{"source":"dashboard_toprail","target":"dashboard_toprail_toprail","relation":"contains","confidence":"EXTRACTED","source_file":"P:\\Projects\\Mycelium\\components\\dashboard\\TopRail.tsx","source_location":"L36","weight":1}]}