{"nodes":[{"id":"finance_revolut_csv","label":"revolut-csv.ts","file_type":"code","source_file":"P:\\Projects\\Mycelium\\lib\\finance\\revolut-csv.ts","source_location":"L1"},{"id":"finance_revolut_csv_parseisodate","label":"parseIsoDate()","file_type":"code","source_file":"P:\\Projects\\Mycelium\\lib\\finance\\revolut-csv.ts","source_location":"L17"},{"id":"finance_revolut_csv_revolutparser","label":"revolutParser","file_type":"code","source_file":"P:\\Projects\\Mycelium\\lib\\finance\\revolut-csv.ts","source_location":"L22"}],"edges":[{"source":"finance_revolut_csv","target":"p_projects_mycelium_lib_finance_csv_parser_ts","relation":"imports_from","confidence":"EXTRACTED","source_file":"P:\\Projects\\Mycelium\\lib\\finance\\revolut-csv.ts","source_location":"L1","weight":1},{"source":"finance_revolut_csv","target":"finance_csv_parser_csvbankparser","relation":"imports","confidence":"EXTRACTED","source_file":"P:\\Projects\\Mycelium\\lib\\finance\\revolut-csv.ts","source_location":"L1","weight":1},{"source":"finance_revolut_csv","target":"finance_csv_parser_accountdescriptor","relation":"imports","confidence":"EXTRACTED","source_file":"P:\\Projects\\Mycelium\\lib\\finance\\revolut-csv.ts","source_location":"L1","weight":1},{"source":"finance_revolut_csv","target":"finance_csv_parser_normalizedtxn","relation":"imports","confidence":"EXTRACTED","source_file":"P:\\Projects\\Mycelium\\lib\\finance\\revolut-csv.ts","source_location":"L1","weight":1},{"source":"finance_revolut_csv","target":"finance_csv_parser_csvparseresult","relation":"imports","confidence":"EXTRACTED","source_file":"P:\\Projects\\Mycelium\\lib\\finance\\revolut-csv.ts","source_location":"L1","weight":1},{"source":"finance_revolut_csv","target":"finance_csv_parser_parseerror","relation":"imports","confidence":"EXTRACTED","source_file":"P:\\Projects\\Mycelium\\lib\\finance\\revolut-csv.ts","source_location":"L1","weight":1},{"source":"finance_revolut_csv","target":"finance_csv_parser_skipinfo","relation":"imports","confidence":"EXTRACTED","source_file":"P:\\Projects\\Mycelium\\lib\\finance\\revolut-csv.ts","source_location":"L1","weight":1},{"source":"finance_revolut_csv","target":"finance_csv_parser_parseamount","relation":"imports","confidence":"EXTRACTED","source_file":"P:\\Projects\\Mycelium\\lib\\finance\\revolut-csv.ts","source_location":"L1","weight":1},{"source":"finance_revolut_csv","target":"finance_csv_parser_splitcsvline","relation":"imports","confidence":"EXTRACTED","source_file":"P:\\Projects\\Mycelium\\lib\\finance\\revolut-csv.ts","source_location":"L1","weight":1},{"source":"finance_revolut_csv","target":"finance_csv_parser_deduphash","relation":"imports","confidence":"EXTRACTED","source_file":"P:\\Projects\\Mycelium\\lib\\finance\\revolut-csv.ts","source_location":"L1","weight":1},{"source":"finance_revolut_csv","target":"finance_csv_parser_normalizelines","relation":"imports","confidence":"EXTRACTED","source_file":"P:\\Projects\\Mycelium\\lib\\finance\\revolut-csv.ts","source_location":"L1","weight":1},{"source":"finance_revolut_csv","target":"finance_revolut_csv_parseisodate","relation":"contains","confidence":"EXTRACTED","source_file":"P:\\Projects\\Mycelium\\lib\\finance\\revolut-csv.ts","source_location":"L17","weight":1},{"source":"finance_revolut_csv","target":"finance_revolut_csv_revolutparser","relation":"contains","confidence":"EXTRACTED","source_file":"P:\\Projects\\Mycelium\\lib\\finance\\revolut-csv.ts","source_location":"L22","weight":1}]}