{"nodes":[{"id":"nutrition_quickbarcodelog","label":"QuickBarcodeLog.tsx","file_type":"code","source_file":"P:\\Projects\\Mycelium\\components\\nutrition\\QuickBarcodeLog.tsx","source_location":"L1"},{"id":"nutrition_quickbarcodelog_quickbarcodelog","label":"QuickBarcodeLog()","file_type":"code","source_file":"P:\\Projects\\Mycelium\\components\\nutrition\\QuickBarcodeLog.tsx","source_location":"L27"},{"id":"nutrition_quickbarcodelog_defaultgroupnamefortime","label":"defaultGroupNameForTime()","file_type":"code","source_file":"P:\\Projects\\Mycelium\\components\\nutrition\\QuickBarcodeLog.tsx","source_location":"L230"}],"edges":[{"source":"nutrition_quickbarcodelog","target":"react","relation":"imports_from","confidence":"EXTRACTED","source_file":"P:\\Projects\\Mycelium\\components\\nutrition\\QuickBarcodeLog.tsx","source_location":"L3","weight":1},{"source":"nutrition_quickbarcodelog","target":"p_projects_mycelium_lib_nutrition_types_v2_ts","relation":"imports_from","confidence":"EXTRACTED","source_file":"P:\\Projects\\Mycelium\\components\\nutrition\\QuickBarcodeLog.tsx","source_location":"L4","weight":1},{"source":"nutrition_quickbarcodelog","target":"nutrition_types_v2_food","relation":"imports","confidence":"EXTRACTED","source_file":"P:\\Projects\\Mycelium\\components\\nutrition\\QuickBarcodeLog.tsx","source_location":"L4","weight":1},{"source":"nutrition_quickbarcodelog","target":"nutrition_types_v2_foodsearchresult","relation":"imports","confidence":"EXTRACTED","source_file":"P:\\Projects\\Mycelium\\components\\nutrition\\QuickBarcodeLog.tsx","source_location":"L4","weight":1},{"source":"nutrition_quickbarcodelog","target":"nutrition_types_v2_mealgroup","relation":"imports","confidence":"EXTRACTED","source_file":"P:\\Projects\\Mycelium\\components\\nutrition\\QuickBarcodeLog.tsx","source_location":"L4","weight":1},{"source":"nutrition_quickbarcodelog","target":"nutrition_types_v2_nutritionlog","relation":"imports","confidence":"EXTRACTED","source_file":"P:\\Projects\\Mycelium\\components\\nutrition\\QuickBarcodeLog.tsx","source_location":"L4","weight":1},{"source":"nutrition_quickbarcodelog","target":"p_projects_mycelium_components_nutrition_barcodescanner_tsx","relation":"imports_from","confidence":"EXTRACTED","source_file":"P:\\Projects\\Mycelium\\components\\nutrition\\QuickBarcodeLog.tsx","source_location":"L10","weight":1},{"source":"nutrition_quickbarcodelog","target":"nutrition_barcodescanner_barcodescanner","relation":"imports","confidence":"EXTRACTED","source_file":"P:\\Projects\\Mycelium\\components\\nutrition\\QuickBarcodeLog.tsx","source_location":"L10","weight":1},{"source":"nutrition_quickbarcodelog","target":"p_projects_mycelium_components_nutrition_servingpicker_tsx","relation":"imports_from","confidence":"EXTRACTED","source_file":"P:\\Projects\\Mycelium\\components\\nutrition\\QuickBarcodeLog.tsx","source_location":"L11","weight":1},{"source":"nutrition_quickbarcodelog","target":"nutrition_servingpicker_servingpicker","relation":"imports","confidence":"EXTRACTED","source_file":"P:\\Projects\\Mycelium\\components\\nutrition\\QuickBarcodeLog.tsx","source_location":"L11","weight":1},{"source":"nutrition_quickbarcodelog","target":"p_projects_mycelium_components_nutrition_manualfoodentry_tsx","relation":"imports_from","confidence":"EXTRACTED","source_file":"P:\\Projects\\Mycelium\\components\\nutrition\\QuickBarcodeLog.tsx","source_location":"L12","weight":1},{"source":"nutrition_quickbarcodelog","target":"nutrition_manualfoodentry_manualfoodentry","relation":"imports","confidence":"EXTRACTED","source_file":"P:\\Projects\\Mycelium\\components\\nutrition\\QuickBarcodeLog.tsx","source_location":"L12","weight":1},{"source":"nutrition_quickbarcodelog","target":"nutrition_quickbarcodelog_quickbarcodelog","relation":"contains","confidence":"EXTRACTED","source_file":"P:\\Projects\\Mycelium\\components\\nutrition\\QuickBarcodeLog.tsx","source_location":"L27","weight":1},{"source":"nutrition_quickbarcodelog","target":"nutrition_quickbarcodelog_defaultgroupnamefortime","relation":"contains","confidence":"EXTRACTED","source_file":"P:\\Projects\\Mycelium\\components\\nutrition\\QuickBarcodeLog.tsx","source_location":"L230","weight":1}]}